client/__init__.py
client/common/__init__.py
client/common/decos.py
client/common/descriptors.py
client/common/errors.py
client/common/metaclasses.py
client/common/utils.py
client/common/variables.py
my_very_best_mess_client-0.1.0.dist-info/METADATA
my_very_best_mess_client-0.1.0.dist-info/WHEEL
my_very_best_mess_client-0.1.0.dist-info/top_level.txt
my_very_best_mess_client-0.1.0.dist-info/RECORD
