Metadata-Version: 2.1
Name: my-very-best-mess-client
Version: 0.1.0
Summary: Mess Client Mess
Home-page: UNKNOWN
Author: Alexey Larin
Author-email: larin_aleksey93@mail.ru
License: UNKNOWN
Platform: UNKNOWN
Requires-Dist: PyQt5
Requires-Dist: sqlalchemy
Requires-Dist: pycryptodome
Requires-Dist: pycryptodomex
